pip_project_square/init.py
pip_project_square/module.py
pip_project_square-1.0.0.dist-info/METADATA
pip_project_square-1.0.0.dist-info/WHEEL
pip_project_square-1.0.0.dist-info/top_level.txt
pip_project_square-1.0.0.dist-info/RECORD
