Metadata-Version: 2.1
Name: pip_project_square
Version: 1.0.0
Summary: A project that calculates the square of a number
Home-page: UNKNOWN
Author: Jalla Vidya Sagar
Author-email: jallavidya.sagar@icloud.com
License: UNKNOWN
Platform: UNKNOWN
